overwatch/__init__.py
overwatch/cli.py
overwatch/api/__init__.py
overwatch/api/admin.py
overwatch/api/audit.py
overwatch/api/auth.py
overwatch/api/config.py
overwatch/api/crud.py
overwatch/api/dashboard.py
overwatch/api/organizations.py
overwatch/api/permissions.py
overwatch/core/__init__.py
overwatch/core/config.py
overwatch/core/database.py
overwatch/middleware/__init__.py
overwatch/middleware/auth.py
overwatch/models/__init__.py
overwatch/models/admin.py
overwatch/models/admin_permission.py
overwatch/models/admin_session.py
overwatch/models/audit_log.py
overwatch/models/config.py
overwatch/models/organization.py
overwatch/schemas/__init__.py
overwatch/schemas/admin.py
overwatch/schemas/config.py
overwatch/schemas/crud.py
overwatch/schemas/organization.py
overwatch/services/__init__.py
overwatch/services/admin_service.py
overwatch/services/config_service.py
overwatch/services/crud_service.py
overwatch/services/dashboard_service.py
overwatch/services/introspection.py
overwatch/services/organization_service.py
overwatch/services/permission_service.py
overwatch/static/config.json
overwatch/static/index.html
overwatch/static/assets/favicon.ico
overwatch/static/assets/index-0364eea2.js
overwatch/static/assets/index-0364eea2.js.map
overwatch/static/assets/index-03f30d3d.js
overwatch/static/assets/index-03f30d3d.js.map
overwatch/static/assets/index-0f763376.js
overwatch/static/assets/index-0f763376.js.map
overwatch/static/assets/index-16b30a9b.js
overwatch/static/assets/index-16b30a9b.js.map
overwatch/static/assets/index-1b8b5742.js
overwatch/static/assets/index-1b8b5742.js.map
overwatch/static/assets/index-23a52259.js
overwatch/static/assets/index-23a52259.js.map
overwatch/static/assets/index-25b897b2.css
overwatch/static/assets/index-2ef9cb93.js
overwatch/static/assets/index-2ef9cb93.js.map
overwatch/static/assets/index-3072a23a.js
overwatch/static/assets/index-3072a23a.js.map
overwatch/static/assets/index-356feddf.css
overwatch/static/assets/index-3a586b33.js
overwatch_admin-0.1.17.dist-info/METADATA
overwatch_admin-0.1.17.dist-info/WHEEL
overwatch_admin-0.1.17.dist-info/RECORD
