Metadata-Version: 2.4
Name: overwatch-admin
Version: 0.1.17
Summary: Admin panel for FastAPI applications with SQLAlchemy models
Project-URL: Homepage, https://github.com/overwatch/overwatch
Project-URL: Documentation, https://overwatch.readthedocs.io
Project-URL: Repository, https://github.com/overwatch/overwatch
Project-URL: Issues, https://github.com/overwatch/overwatch/issues
Author-email: Overwatch Contributors <contributors@overwatch.dev>
License: MIT
Keywords: admin,crud,dashboard,fastapi,panel,sqlalchemy
Classifier: Development Status :: 4 - Beta
Classifier: Framework :: FastAPI
Classifier: Intended Audience :: Developers
Classifier: License :: OSI Approved :: MIT License
Classifier: Operating System :: OS Independent
Classifier: Programming Language :: Python :: 3
Classifier: Programming Language :: Python :: 3.11
Classifier: Programming Language :: Python :: 3.12
Classifier: Topic :: Internet :: WWW/HTTP :: HTTP Servers
Classifier: Topic :: Software Development :: Libraries :: Application Frameworks
Requires-Python: >=3.11
Requires-Dist: aiofiles>=23.2.1
Requires-Dist: alembic>=1.12.0
Requires-Dist: fastapi>=0.104.0
Requires-Dist: jinja2>=3.1.0
Requires-Dist: openpyxl>=3.1.5
Requires-Dist: passlib[bcrypt]>=1.7.4
Requires-Dist: pydantic-settings>=2.1.0
Requires-Dist: pydantic[email]>=2.5.0
Requires-Dist: python-jose[cryptography]>=3.3.0
Requires-Dist: python-multipart>=0.0.6
Requires-Dist: sqlalchemy>=2.0.0
Provides-Extra: dev
Requires-Dist: black>=23.11.0; extra == 'dev'
Requires-Dist: httpx>=0.25.2; extra == 'dev'
Requires-Dist: isort>=5.12.0; extra == 'dev'
Requires-Dist: mypy>=1.7.1; extra == 'dev'
Requires-Dist: pre-commit>=3.6.0; extra == 'dev'
Requires-Dist: pyrefly>=0.1.3; extra == 'dev'
Requires-Dist: pytest-asyncio>=0.21.1; extra == 'dev'
Requires-Dist: pytest-cov>=4.1.0; extra == 'dev'
Requires-Dist: pytest>=7.4.3; extra == 'dev'
Requires-Dist: ruff>=0.1.6; extra == 'dev'
Provides-Extra: mysql
Requires-Dist: aiomysql>=0.2.0; extra == 'mysql'
Provides-Extra: postgresql
Requires-Dist: asyncpg>=0.29.0; extra == 'postgresql'
Provides-Extra: sqlite
Requires-Dist: aiosqlite>=0.21.0; extra == 'sqlite'
